berrycam/__init__.py
berrycam/berrycam.py
berrycam-0.4.0.dist-info/DESCRIPTION.rst
berrycam-0.4.0.dist-info/METADATA
berrycam-0.4.0.dist-info/RECORD
berrycam-0.4.0.dist-info/WHEEL
berrycam-0.4.0.dist-info/entry_points.txt
berrycam-0.4.0.dist-info/metadata.json
berrycam-0.4.0.dist-info/top_level.txt
