Metadata-Version: 2.0
Name: berrycam
Version: 0.4.0
Summary: berrycam makes taking pictures with your Raspberry Pi easy!
Home-page: https://codedin.wales/picymru/berrycam
Author: PiCymru
Author-email: code@picymru.email
License: MIT
Platform: linux
Classifier: Development Status :: 4 - Beta
Classifier: Environment :: Console
Classifier: Intended Audience :: Developers
Classifier: License :: OSI Approved :: MIT License
Classifier: Programming Language :: Python :: 2
Classifier: Programming Language :: Python :: 3
Requires-Dist: picamera
Requires-Dist: boto3
